setup.py
src/imaris_tools/__init__.py
src/imaris_tools/imaris_tools.py
src/imaris_tools/ims2csv.py
src/imaris_tools.egg-info/PKG-INFO
src/imaris_tools.egg-info/SOURCES.txt
src/imaris_tools.egg-info/dependency_links.txt
src/imaris_tools.egg-info/requires.txt
src/imaris_tools.egg-info/top_level.txt