Metadata-Version: 1.0
Name: imaris-tools
Version: 0.1.6
Summary: manipulation of ims files
Home-page: UNKNOWN
Author: UNKNOWN
Author-email: UNKNOWN
License: UNKNOWN
Platform: UNKNOWN
